[
  { "name":"shawnN","dimension": 1,"value": 260 },
  [
    [
      { "name":"chilton","dimension": 1,"value": 150 },
      { "name":"sean","dimension": 1,"value": 60 },
      { "name":"tmerrill","dimension": 1,"value": 110 },
      { "name":"joshg","dimension": 1,"value": 60 },
      [
        { "name":"rchrastil","dimension": 0,"value": 35 },
        { "name":"lhealy","dimension": 0,"value": 35 }
      ]
    ],
    [
      [
        { "name":"jkelly","dimension": 0,"value": 60 },
        { "name":"dmoore","dimension": 0,"value": 60 }
      ],
      [
        [
          { "name":"aneubert","dimension": 1,"value": 35 },
          { "name":"clarkh","dimension": 1,"value": 60 }
        ],
        { "name":"hollyl","dimension": 0,"value": 110 }
      ],
      { "name":"mdtommyd","dimension": 1,"value": 150 },
      [
        { "name":"garyl","dimension": 0,"value": 60 },
        { "name":"mchackett","dimension": 0,"value": 60 }
      ]
    ]
  ],
  { "name":"rsmith","dimension": 1,"value": 510 }
]
